{"dramaSite":"gimy.ai","dramaTitle":"珍饈記","dramaUrl":"https:\/\/gimy.ai\/vod\/196483.html","dramaId":"196483","dramaCoverUrl":"https:\/\/img.1777cdn.com\/upload\/vod\/20220417-1\/8561ec45e77348f0e4106d8faf933b2f.png","filmSources":[{"filmSourceName":"B站線路 ᴴᴰ","episodes":[{"episodeId":"196483-01-001","episodeName":"第1集","episodeUrl":"https:\/\/www.bilibili.com\/bangumi\/play\/ep478152"},{"episodeId":"196483-01-002","episodeName":"第2集","episodeUrl":"https:\/\/www.bilibili.com\/bangumi\/play\/ep478162"},{"episodeId":"196483-01-003","episodeUrl":"https:\/\/www.bilibili.com\/bangumi\/play\/ep478166","episodeName":"第3集"},{"episodeUrl":"https:\/\/www.bilibili.com\/bangumi\/play\/ep478179","episodeName":"第4集","episodeId":"196483-01-004"},{"episodeUrl":"https:\/\/www.bilibili.com\/bangumi\/play\/ep478455","episodeId":"196483-01-005","episodeName":"第5集"},{"episodeId":"196483-01-006","episodeName":"第6集","episodeUrl":"https:\/\/www.bilibili.com\/bangumi\/play\/ep478538"},{"episodeId":"196483-01-007","episodeName":"第7集","episodeUrl":"https:\/\/www.bilibili.com\/bangumi\/play\/ep479514"},{"episodeName":"第8集","episodeUrl":"https:\/\/www.bilibili.com\/bangumi\/play\/ep479515","episodeId":"196483-01-008"},{"episodeUrl":"https:\/\/www.bilibili.com\/bangumi\/play\/ep479516","episodeName":"第9集","episodeId":"196483-01-009"},{"episodeId":"196483-01-010","episodeName":"第10集","episodeUrl":"https:\/\/www.bilibili.com\/bangumi\/play\/ep480923"},{"episodeUrl":"https:\/\/www.bilibili.com\/bangumi\/play\/ep480924","episodeId":"196483-01-011","episodeName":"第11集"},{"episodeId":"196483-01-012","episodeName":"第12集","episodeUrl":"https:\/\/www.bilibili.com\/bangumi\/play\/ep480925"},{"episodeId":"196483-01-013","episodeUrl":"https:\/\/www.bilibili.com\/bangumi\/play\/ep508524","episodeName":"第13集"},{"episodeUrl":"https:\/\/www.bilibili.com\/bangumi\/play\/ep508525","episodeId":"196483-01-014","episodeName":"第14集"},{"episodeId":"196483-01-015","episodeName":"第15集","episodeUrl":"https:\/\/www.bilibili.com\/bangumi\/play\/ep508526"},{"episodeName":"第16集","episodeId":"196483-01-016","episodeUrl":"https:\/\/www.bilibili.com\/bangumi\/play\/ep508527"}],"filmSourceId":"196483-01"},{"episodes":[{"episodeUrl":"https:\/\/v6.1080pzy.co\/20220802\/4ego699B\/index.m3u8","episodeName":"第01集","episodeId":"196483-02-001"},{"episodeId":"196483-02-002","episodeName":"第02集","episodeUrl":"https:\/\/v6.1080pzy.co\/20220802\/XabCi3mX\/index.m3u8"},{"episodeId":"196483-02-003","episodeUrl":"https:\/\/v6.1080pzy.co\/20220802\/HNi5DrBT\/index.m3u8","episodeName":"第03集"},{"episodeUrl":"https:\/\/v6.1080pzy.co\/20220802\/WFVCpJk5\/index.m3u8","episodeId":"196483-02-004","episodeName":"第04集"},{"episodeUrl":"https:\/\/v6.1080pzy.co\/20220802\/7YPgA3sZ\/index.m3u8","episodeName":"第05集","episodeId":"196483-02-005"},{"episodeName":"第06集","episodeId":"196483-02-006","episodeUrl":"https:\/\/v6.1080pzy.co\/20220802\/g3EylE5I\/index.m3u8"},{"episodeUrl":"https:\/\/v6.1080pzy.co\/20220802\/QWhMEbdu\/index.m3u8","episodeName":"第07集","episodeId":"196483-02-007"},{"episodeId":"196483-02-008","episodeName":"第08集","episodeUrl":"https:\/\/v6.1080pzy.co\/20220802\/UCbziaDu\/index.m3u8"},{"episodeName":"第09集","episodeUrl":"https:\/\/v6.1080pzy.co\/20220802\/ypI10Qbm\/index.m3u8","episodeId":"196483-02-009"},{"episodeId":"196483-02-010","episodeName":"第10集","episodeUrl":"https:\/\/v6.1080pzy.co\/20220802\/hJW4iFKl\/index.m3u8"},{"episodeId":"196483-02-011","episodeName":"第11集","episodeUrl":"https:\/\/v6.1080pzy.co\/20220802\/77xrMk0F\/index.m3u8"},{"episodeName":"第12集","episodeUrl":"https:\/\/v6.1080pzy.co\/20220802\/amE2J41V\/index.m3u8","episodeId":"196483-02-012"},{"episodeId":"196483-02-013","episodeUrl":"https:\/\/v6.1080pzy.co\/20220802\/QO7QYaPp\/index.m3u8","episodeName":"第13集"},{"episodeId":"196483-02-014","episodeName":"第14集","episodeUrl":"https:\/\/v6.1080pzy.co\/20220802\/HbsWuoL5\/index.m3u8"},{"episodeId":"196483-02-015","episodeName":"第15集","episodeUrl":"https:\/\/v6.1080pzy.co\/20220802\/ieVsWv59\/index.m3u8"},{"episodeUrl":"https:\/\/v6.1080pzy.co\/20220802\/IHq9VWuX\/index.m3u8","episodeId":"196483-02-016","episodeName":"第16集"}],"filmSourceId":"196483-02","filmSourceName":"飛速雲"},{"filmSourceName":"速播雲","filmSourceId":"196483-03","episodes":[{"episodeUrl":"https:\/\/1080p.sbzyplay.com\/play\/Ddwyr8wa\/index.m3u8","episodeName":"第1集","episodeId":"196483-03-001"},{"episodeUrl":"https:\/\/1080p.sbzyplay.com\/play\/YaOX8kNb\/index.m3u8","episodeId":"196483-03-002","episodeName":"第2集"},{"episodeId":"196483-03-003","episodeName":"第3集","episodeUrl":"https:\/\/1080p.sbzyplay.com\/play\/Rb4vLD6e\/index.m3u8"},{"episodeUrl":"https:\/\/1080p.sbzyplay.com\/play\/mepo2K2d\/index.m3u8","episodeId":"196483-03-004","episodeName":"第4集"},{"episodeUrl":"https:\/\/1080p.sbzyplay.com\/play\/PdyAX5Wd\/index.m3u8","episodeId":"196483-03-005","episodeName":"第5集"},{"episodeName":"第6集","episodeId":"196483-03-006","episodeUrl":"https:\/\/1080p.sbzyplay.com\/play\/penmOVld\/index.m3u8"},{"episodeUrl":"https:\/\/1080p.sbzyplay.com\/play\/rb2qWova\/index.m3u8","episodeId":"196483-03-007","episodeName":"第7集"},{"episodeId":"196483-03-008","episodeUrl":"https:\/\/1080p.sbzyplay.com\/play\/BeXX5wme\/index.m3u8","episodeName":"第8集"},{"episodeId":"196483-03-009","episodeUrl":"https:\/\/1080p.sbzyplay.com\/play\/DbDZ87ne\/index.m3u8","episodeName":"第9集"},{"episodeUrl":"https:\/\/1080p.sbzyplay.com\/play\/mepo2K6d\/index.m3u8","episodeId":"196483-03-010","episodeName":"第10集"},{"episodeName":"第11集","episodeId":"196483-03-011","episodeUrl":"https:\/\/1080p.sbzyplay.com\/play\/1aMK1m3d\/index.m3u8"},{"episodeId":"196483-03-012","episodeName":"第12集","episodeUrl":"https:\/\/1080p.sbzyplay.com\/play\/5eV2Qy1e\/index.m3u8"},{"episodeName":"第13集","episodeUrl":"https:\/\/1080p.sbzyplay.com\/play\/RdGX8x0e\/index.m3u8","episodeId":"196483-03-013"},{"episodeName":"第14集","episodeUrl":"https:\/\/1080p.sbzyplay.com\/play\/Xe0oLyXd\/index.m3u8","episodeId":"196483-03-014"},{"episodeId":"196483-03-015","episodeUrl":"https:\/\/1080p.sbzyplay.com\/play\/yb8zExoe\/index.m3u8","episodeName":"第15集"},{"episodeName":"第16集完結","episodeUrl":"https:\/\/1080p.sbzyplay.com\/play\/lejg8M5a\/index.m3u8","episodeId":"196483-03-016"}]},{"episodes":[{"episodeName":"第01集","episodeUrl":"https:\/\/v3.dious.cc\/20220407\/WsVMsVDv\/index.m3u8","episodeId":"196483-04-001"},{"episodeId":"196483-04-002","episodeUrl":"https:\/\/v3.dious.cc\/20220407\/E60oceIo\/index.m3u8","episodeName":"第02集"},{"episodeName":"第03集","episodeUrl":"https:\/\/v3.dious.cc\/20220407\/jNb6pACd\/index.m3u8","episodeId":"196483-04-003"},{"episodeUrl":"https:\/\/v6.dious.cc\/20220414\/OTHHgzUA\/index.m3u8","episodeName":"第04集","episodeId":"196483-04-004"},{"episodeName":"第05集","episodeId":"196483-04-005","episodeUrl":"https:\/\/v6.dious.cc\/20220414\/caRKckKE\/index.m3u8"},{"episodeId":"196483-04-006","episodeUrl":"https:\/\/v6.dious.cc\/20220414\/Ljym6K4w\/index.m3u8","episodeName":"第06集"},{"episodeName":"第07集","episodeId":"196483-04-007","episodeUrl":"https:\/\/v6.dious.cc\/20220421\/W1L6VRkQ\/index.m3u8"},{"episodeName":"第08集","episodeUrl":"https:\/\/v6.dious.cc\/20220421\/f7A8qW6c\/index.m3u8","episodeId":"196483-04-008"},{"episodeName":"第09集","episodeUrl":"https:\/\/v6.dious.cc\/20220421\/zLaSBxoD\/index.m3u8","episodeId":"196483-04-009"},{"episodeName":"第10集","episodeUrl":"https:\/\/v6.dious.cc\/20220428\/qAUVHSO2\/index.m3u8","episodeId":"196483-04-010"},{"episodeId":"196483-04-011","episodeName":"第11集","episodeUrl":"https:\/\/v6.dious.cc\/20220428\/Zt5qL9dp\/index.m3u8"},{"episodeUrl":"https:\/\/v6.dious.cc\/20220428\/3HwZE8Pv\/index.m3u8","episodeId":"196483-04-012","episodeName":"第12集"},{"episodeId":"196483-04-013","episodeName":"第13集","episodeUrl":"https:\/\/v6.dious.cc\/20220502\/pVGf0qFQ\/index.m3u8"},{"episodeId":"196483-04-014","episodeUrl":"https:\/\/v6.dious.cc\/20220502\/XTHaxIL7\/index.m3u8","episodeName":"第14集"},{"episodeName":"第15集","episodeUrl":"https:\/\/v6.dious.cc\/20220502\/vJJCiPzp\/index.m3u8","episodeId":"196483-04-015"},{"episodeId":"196483-04-016","episodeName":"第16集","episodeUrl":"https:\/\/v6.dious.cc\/20220502\/MqhPwowu\/index.m3u8"},{"episodeUrl":"https:\/\/v6.dious.cc\/20220503\/B2G19fjP\/index.m3u8","episodeId":"196483-04-017","episodeName":"番外"}],"filmSourceName":"天空雲","filmSourceId":"196483-04"},{"filmSourceName":"量子雲","episodes":[{"episodeName":"第01集","episodeId":"196483-05-001","episodeUrl":"https:\/\/vip.lz-cdn8.com\/20220523\/10036_b439638a\/index.m3u8"},{"episodeId":"196483-05-002","episodeUrl":"https:\/\/vip.lz-cdn8.com\/20220523\/10037_211dcd28\/index.m3u8","episodeName":"第02集"},{"episodeUrl":"https:\/\/vip.lz-cdn8.com\/20220523\/10038_6e46f8a9\/index.m3u8","episodeId":"196483-05-003","episodeName":"第03集"},{"episodeId":"196483-05-004","episodeUrl":"https:\/\/vip.lz-cdn8.com\/20220523\/10039_5bf416e1\/index.m3u8","episodeName":"第04集"},{"episodeName":"第05集","episodeUrl":"https:\/\/vip.lz-cdn8.com\/20220523\/10040_98c82f45\/index.m3u8","episodeId":"196483-05-005"},{"episodeName":"第06集","episodeUrl":"https:\/\/vip.lz-cdn8.com\/20220523\/10041_3883665c\/index.m3u8","episodeId":"196483-05-006"},{"episodeName":"第07集","episodeId":"196483-05-007","episodeUrl":"https:\/\/vip.lz-cdn8.com\/20220523\/10042_cc35d90e\/index.m3u8"},{"episodeName":"第08集","episodeUrl":"https:\/\/vip.lz-cdn8.com\/20220523\/10043_3d705acc\/index.m3u8","episodeId":"196483-05-008"},{"episodeId":"196483-05-009","episodeUrl":"https:\/\/vip.lz-cdn8.com\/20220523\/10044_6174055c\/index.m3u8","episodeName":"第09集"},{"episodeId":"196483-05-010","episodeName":"第10集","episodeUrl":"https:\/\/vip.lz-cdn8.com\/20220523\/10045_74fd4615\/index.m3u8"},{"episodeUrl":"https:\/\/vip.lz-cdn8.com\/20220523\/10046_199d180f\/index.m3u8","episodeId":"196483-05-011","episodeName":"第11集"},{"episodeId":"196483-05-012","episodeName":"第12集","episodeUrl":"https:\/\/vip.lz-cdn8.com\/20220523\/10047_c57fcdd1\/index.m3u8"},{"episodeName":"第13集","episodeUrl":"https:\/\/vip.lz-cdn8.com\/20220523\/10048_94e9a7dc\/index.m3u8","episodeId":"196483-05-013"},{"episodeId":"196483-05-014","episodeName":"第14集","episodeUrl":"https:\/\/vip.lz-cdn8.com\/20220523\/10049_e8ee31e4\/index.m3u8"},{"episodeName":"第15集","episodeUrl":"https:\/\/vip.lz-cdn8.com\/20220523\/10050_df0146f9\/index.m3u8","episodeId":"196483-05-015"},{"episodeName":"第16集","episodeUrl":"https:\/\/vip.lz-cdn8.com\/20220523\/10051_b61bb3c3\/index.m3u8","episodeId":"196483-05-016"}],"filmSourceId":"196483-05"}]}